{
  "profile": "MIN_LOT_FALLBACK_V1",
  "starting_capital": 10000.0,
  "final_equity": 10008.03,
  "cagr": 0.00038,
  "cagr_pct": 0.038,
  "max_drawdown_usd": 335.54,
  "max_drawdown_pct": 3.297,
  "mar": 0.0115,
  "total_accepted": 31,
  "total_rejected": 1,
  "rejection_rate_pct": 3.12,
  "max_concurrent_trades": 1,
  "configured_concurrency_cap": null,
  "avg_heat_utilization_pct": 0.0,
  "pct_time_at_full_heat": 0.0,
  "longest_loss_streak": 3,
  "realized_pnl": 8.03,
  "simulation_years": 2.12,
  "risk_override_rate": 96.77,
  "avg_risk_multiple": 1.54,
  "max_risk_multiple": 2.19
}