{
  "profile": "MIN_LOT_FALLBACK_UNCAPPED_V1",
  "starting_capital": 10000.0,
  "final_equity": 12637.19,
  "cagr": 0.183032,
  "cagr_pct": 18.3032,
  "max_drawdown_usd": 639.2,
  "max_drawdown_pct": 5.0209,
  "mar": 3.6454,
  "total_accepted": 2432,
  "total_rejected": 159,
  "rejection_rate_pct": 6.14,
  "max_concurrent_trades": 4,
  "configured_concurrency_cap": null,
  "avg_heat_utilization_pct": 0.1598,
  "pct_time_at_full_heat": 0.0,
  "longest_loss_streak": 12,
  "realized_pnl": 2637.19,
  "simulation_years": 1.39,
  "risk_override_rate": 0.0,
  "avg_risk_multiple": 0.0,
  "max_risk_multiple": 0.0
}